{
  "6": {
    "inputs": {
      "image": "background (32).jpg",
      "upload": "image"
    },
    "class_type": "LoadImage",
    "_meta": {
      "title": "Load Image"
    }
  },
  "9": {
    "inputs": {
      "root_dir": "output",
      "file": "caption.txt",
      "append": "new only",
      "insert": false,
      "text": [
        "12",
        0
      ]
    },
    "class_type": "SaveText|pysssss",
    "_meta": {
      "title": "Save Text 🐍"
    }
  },
  "10": {
    "inputs": {
      "caption_type": "Descriptive",
      "caption_length": "very long",
      "low_vram": false,
      "joy_two_pipeline": [
        "11",
        0
      ],
      "image": [
        "6",
        0
      ]
    },
    "class_type": "Joy_caption_two",
    "_meta": {
      "title": "Joy Caption Two"
    }
  },
  "11": {
    "inputs": {
      "model": "John6666/Llama-3.1-8B-Lexi-Uncensored-V2-nf4"
    },
    "class_type": "Joy_caption_two_load",
    "_meta": {
      "title": "Joy Caption Two Load"
    }
  },
  "12": {
    "inputs": {
      "text": [
        "10",
        0
      ],
      "text2": "The image is a photograph taken in a modern, well-lit shopping mall. The central subject is a young woman of East Asian descent with a fair complexion and long, straight, dark brown hair that cascades over her shoulders. She is smiling warmly, her lips slightly parted, revealing her straight white teeth. She wears a strapless white ruffled crop top that highlights her slender physique and small breasts. Her bottom attire consists of high-waisted, red floral pants that complement her outfit. She accessorizes with a silver bracelet on her left wrist and a small pendant necklace. A large, grey handbag with a chain strap hangs over her right shoulder.\n\nThe background shows a bustling shopping mall with blurred figures of other shoppers and store displays. The mall has a modern, clean design with white and light blue tones. The ceiling features large rectangular light fixtures. The overall atmosphere is bright and lively, with a sense of casual elegance and youthful energy. The photograph captures a candid, spontaneous moment, emphasizing the subject's cheerful and approachable demeanor."
    },
    "class_type": "ShowText|pysssss",
    "_meta": {
      "title": "Show Text 🐍"
    }
  }
}